<?xml version="1.0" ?>
<request>
	<mouseAnatomyReport>
		<stage>
			TS01
		</stage>
		<groupStatusKey>
			<groupStatus status="notInGroupPath">
				Term is not a group nor is it contained in a group.
			</groupStatus>
			<groupStatus status="isGroup">
				Term a group
			</groupStatus>
			<groupStatus status="isGroupDirectDescendant">
				Term is directly contained in a group.
			</groupStatus>
			<groupStatus status="isGroupIndirectDescendant">
				Term is indirectly contained in a group.
			</groupStatus>
		</groupStatusKey>
		<timedComponent emapId="EMAP:0025766">
			<name emapId="EMAP:0025766">
				mouse
			</name>
			<emapaId emapId="EMAP:0025766">
				EMAPA:0025765
			</emapaId>
			<groupPathStatus emapId="EMAP:0025766">
				notInGroupPath
			</groupPathStatus>
			<timedComponent emapId="EMAP:0000001">
				<name emapId="EMAP:0000001">
					first polar body
				</name>
				<emapaId emapId="EMAP:0000001">
					EMAPA:0016032
				</emapaId>
				<groupPathStatus emapId="EMAP:0000001">
					notInGroupPath
				</groupPathStatus>
			</timedComponent>
			<timedComponent emapId="EMAP:0000002">
				<name emapId="EMAP:0000002">
					one-cell stage embryo
				</name>
				<emapaId emapId="EMAP:0000002">
					EMAPA:0016033
				</emapaId>
				<groupPathStatus emapId="EMAP:0000002">
					notInGroupPath
				</groupPathStatus>
			</timedComponent>
			<timedComponent emapId="EMAP:0031909">
				<name emapId="EMAP:0031909">
					polar body group
				</name>
				<emapaId emapId="EMAP:0031909">
					EMAPA:0031859
				</emapaId>
				<groupPathStatus emapId="EMAP:0031909">
					notInGroupPath
				</groupPathStatus>
				<timedComponent emapId="EMAP:0000001">
					<name emapId="EMAP:0000001">
						first polar body
					</name>
					<emapaId emapId="EMAP:0000001">
						EMAPA:0016032
					</emapaId>
					<groupPathStatus emapId="EMAP:0000001">
						notInGroupPath
					</groupPathStatus>
				</timedComponent>
				<timedComponent emapId="EMAP:0000003">
					<name emapId="EMAP:0000003">
						second polar body
					</name>
					<emapaId emapId="EMAP:0000003">
						EMAPA:0016034
					</emapaId>
					<groupPathStatus emapId="EMAP:0000003">
						notInGroupPath
					</groupPathStatus>
				</timedComponent>
			</timedComponent>
			<timedComponent emapId="EMAP:0000003">
				<name emapId="EMAP:0000003">
					second polar body
				</name>
				<emapaId emapId="EMAP:0000003">
					EMAPA:0016034
				</emapaId>
				<groupPathStatus emapId="EMAP:0000003">
					notInGroupPath
				</groupPathStatus>
			</timedComponent>
			<timedComponent emapId="EMAP:0000004">
				<name emapId="EMAP:0000004">
					zona pellucida
				</name>
				<emapaId emapId="EMAP:0000004">
					EMAPA:0016035
				</emapaId>
				<groupPathStatus emapId="EMAP:0000004">
					notInGroupPath
				</groupPathStatus>
			</timedComponent>
		</timedComponent>
	</mouseAnatomyReport>
	<anatomyDatabaseVersion date="2012-11-13 11:54:09" number="11"/>
	<perspective>
		Whole mouse
	</perspective>
</request>
