{"node":{"nodeId":"1","extId":"EMAP:25776","name":"mouse","children":[{"node":{"nodeId":"2","extId":"EMAP:170","name":"organ system","children":[{"node":{"nodeId":"3","extId":"EMAP:171","name":"cardiovascular system","children":[{"node":{"nodeId":"4","extId":"EMAP:172","name":"heart","children":[{"node":{"nodeId":"5","extId":"EMAP:173","name":"cardiogenic plate"}}]}}]}}]}},{"node":{"nodeId":"6","extId":"EMAP:148","name":"cavities and their linings","children":[{"node":{"nodeId":"7","extId":"EMAP:149","name":"intraembryonic coelom"}}]}},{"node":{"nodeId":"8","extId":"EMAP:150","name":"ectoderm","children":[{"node":{"nodeId":"9","extId":"EMAP:151","name":"neural ectoderm","children":[{"node":{"nodeId":"10","extId":"EMAP:152","name":"future brain","children":[{"node":{"nodeId":"11","extId":"EMAP:153","name":"neural fold","children":[{"node":{"nodeId":"12","extId":"EMAP:154","name":"neural crest"}}]}}]}},{"node":{"nodeId":"13","extId":"EMAP:155","name":"future spinal cord","children":[{"node":{"nodeId":"14","extId":"EMAP:156","name":"neural fold","children":[{"node":{"nodeId":"15","extId":"EMAP:157","name":"neural crest"}}]}},{"node":{"nodeId":"16","extId":"EMAP:158","name":"neural plate"}}]}}]}},{"node":{"nodeId":"17","extId":"EMAP:159","name":"surface ectoderm"}}]}},{"node":{"nodeId":"18","extId":"EMAP:160","name":"endoderm","children":[{"node":{"nodeId":"19","extId":"EMAP:161","name":"definitive endoderm"}},{"node":{"nodeId":"20","extId":"EMAP:162","name":"primitive endoderm"}}]}},{"node":{"nodeId":"21","extId":"EMAP:176","name":"extraembryonic component","children":[{"node":{"nodeId":"22","extId":"EMAP:177","name":"allantois","children":[{"node":{"nodeId":"23","extId":"EMAP:178","name":"allantois mesoderm"}}]}},{"node":{"nodeId":"24","extId":"EMAP:179","name":"amnion","children":[{"node":{"nodeId":"25","extId":"EMAP:180","name":"amnion ectoderm"}},{"node":{"nodeId":"26","extId":"EMAP:181","name":"amnion mesoderm"}}]}},{"node":{"nodeId":"27","extId":"EMAP:187","name":"chorion","children":[{"node":{"nodeId":"28","extId":"EMAP:188","name":"chorion ectoderm"}},{"node":{"nodeId":"29","extId":"EMAP:32107","name":"chorion mesenchyme"}},{"node":{"nodeId":"30","extId":"EMAP:189","name":"chorion mesoderm"}}]}},{"node":{"nodeId":"31","extId":"EMAP:182","name":"extraembryonic component cavities","children":[{"node":{"nodeId":"32","extId":"EMAP:183","name":"amniotic cavity"}},{"node":{"nodeId":"33","extId":"EMAP:184","name":"ectoplacental cavity"}},{"node":{"nodeId":"34","extId":"EMAP:185","name":"exocoelomic cavity"}},{"node":{"nodeId":"35","extId":"EMAP:186","name":"yolk sac cavity"}}]}},{"node":{"nodeId":"36","extId":"EMAP:32167","name":"extraembryonic ectoderm"}},{"node":{"nodeId":"37","extId":"EMAP:190","name":"extraembryonic endoderm","children":[{"node":{"nodeId":"38","extId":"EMAP:191","name":"intermediate endoderm"}},{"node":{"nodeId":"39","extId":"EMAP:192","name":"parietal endoderm","children":[{"node":{"nodeId":"40","extId":"EMAP:193","name":"Reichert's membrane"}}]}},{"node":{"nodeId":"41","extId":"EMAP:194","name":"visceral endoderm"}}]}},{"node":{"nodeId":"42","extId":"EMAP:31917","name":"extraembryonic mesenchyme"}},{"node":{"nodeId":"43","extId":"EMAP:31916","name":"extraembryonic mesoderm"}},{"node":{"nodeId":"44","extId":"EMAP:195","name":"trophectoderm","children":[{"node":{"nodeId":"45","extId":"EMAP:196","name":"mural trophectoderm","children":[{"node":{"nodeId":"46","extId":"EMAP:197","name":"primary trophoblast giant cells"}}]}},{"node":{"nodeId":"47","extId":"EMAP:198","name":"polar trophectoderm","children":[{"node":{"nodeId":"48","extId":"EMAP:199","name":"ectoplacental cone","children":[{"node":{"nodeId":"49","extId":"EMAP:200","name":"cytotrophoblast"}},{"node":{"nodeId":"50","extId":"EMAP:201","name":"syncytiotrophoblast"}}]}}]}}]}},{"node":{"nodeId":"51","extId":"EMAP:202","name":"yolk sac","children":[{"node":{"nodeId":"52","extId":"EMAP:203","name":"yolk sac endoderm"}},{"node":{"nodeId":"53","extId":"EMAP:204","name":"yolk sac mesoderm","children":[{"node":{"nodeId":"54","extId":"EMAP:205","name":"blood island"}},{"node":{"nodeId":"55","extId":"EMAP:206","name":"primordial germ cells"}}]}}]}}]}},{"node":{"nodeId":"56","extId":"EMAP:163","name":"mesenchyme","children":[{"node":{"nodeId":"57","extId":"EMAP:164","name":"head mesenchyme","children":[{"node":{"nodeId":"58","extId":"EMAP:165","name":"mesenchyme derived from head mesoderm","children":[{"node":{"nodeId":"59","extId":"EMAP:15246","name":"mesenchyme derived from somites 01-04"}}]}},{"node":{"nodeId":"60","extId":"EMAP:166","name":"mesenchyme derived from neural-crest"}}]}}]}},{"node":{"nodeId":"61","extId":"EMAP:167","name":"mesoderm"}},{"node":{"nodeId":"62","extId":"EMAP:168","name":"notochordal plate"}},{"node":{"nodeId":"63","extId":"EMAP:169","name":"notochordal process"}},{"node":{"nodeId":"64","extId":"EMAP:174","name":"primitive streak","children":[{"node":{"nodeId":"65","extId":"EMAP:175","name":"node"}}]}},{"node":{"nodeId":"66","extId":"EMAP:170","name":"organ system"}},{"node":{"nodeId":"67","extId":"EMAP:147","name":"embryo","children":[{"node":{"nodeId":"68","extId":"EMAP:148","name":"cavities and their linings","children":[{"node":{"nodeId":"69","extId":"EMAP:149","name":"intraembryonic coelom"}}]}},{"node":{"nodeId":"70","extId":"EMAP:150","name":"ectoderm","children":[{"node":{"nodeId":"71","extId":"EMAP:151","name":"neural ectoderm","children":[{"node":{"nodeId":"72","extId":"EMAP:152","name":"future brain","children":[{"node":{"nodeId":"73","extId":"EMAP:153","name":"neural fold","children":[{"node":{"nodeId":"74","extId":"EMAP:154","name":"neural crest"}}]}}]}},{"node":{"nodeId":"75","extId":"EMAP:155","name":"future spinal cord","children":[{"node":{"nodeId":"76","extId":"EMAP:156","name":"neural fold","children":[{"node":{"nodeId":"77","extId":"EMAP:157","name":"neural crest"}}]}},{"node":{"nodeId":"78","extId":"EMAP:158","name":"neural plate"}}]}}]}},{"node":{"nodeId":"79","extId":"EMAP:159","name":"surface ectoderm"}}]}},{"node":{"nodeId":"80","extId":"EMAP:160","name":"endoderm","children":[{"node":{"nodeId":"81","extId":"EMAP:161","name":"definitive endoderm"}},{"node":{"nodeId":"82","extId":"EMAP:162","name":"primitive endoderm"}}]}},{"node":{"nodeId":"83","extId":"EMAP:163","name":"mesenchyme","children":[{"node":{"nodeId":"84","extId":"EMAP:164","name":"head mesenchyme","children":[{"node":{"nodeId":"85","extId":"EMAP:165","name":"mesenchyme derived from head mesoderm","children":[{"node":{"nodeId":"86","extId":"EMAP:15246","name":"mesenchyme derived from somites 01-04"}}]}},{"node":{"nodeId":"87","extId":"EMAP:166","name":"mesenchyme derived from neural-crest"}}]}}]}},{"node":{"nodeId":"88","extId":"EMAP:167","name":"mesoderm"}},{"node":{"nodeId":"89","extId":"EMAP:168","name":"notochordal plate"}},{"node":{"nodeId":"90","extId":"EMAP:169","name":"notochordal process"}},{"node":{"nodeId":"91","extId":"EMAP:170","name":"organ system","children":[{"node":{"nodeId":"92","extId":"EMAP:171","name":"cardiovascular system","children":[{"node":{"nodeId":"93","extId":"EMAP:172","name":"heart","children":[{"node":{"nodeId":"94","extId":"EMAP:173","name":"cardiogenic plate"}}]}}]}}]}},{"node":{"nodeId":"95","extId":"EMAP:174","name":"primitive streak","children":[{"node":{"nodeId":"96","extId":"EMAP:175","name":"node"}}]}}]}},{"node":{"nodeId":"97","extId":"EMAP:163","name":"mesenchyme"}}]}}